openlane/__init__.py
openlane/__main__.py
openlane/__version__.py
openlane/common/__init__.py
openlane/common/cli.py
openlane/common/drc.py
openlane/common/generic_dict.py
openlane/common/metrics/__init__.py
openlane/common/metrics/__main__.py
openlane/common/metrics/library.py
openlane/common/metrics/metric.py
openlane/common/metrics/util.py
openlane/common/misc.py
openlane/common/ring_buffer.py
openlane/common/tcl.py
openlane/common/toolbox.py
openlane/common/tpe.py
openlane/common/types.py
openlane/config/__init__.py
openlane/config/__main__.py
openlane/config/config.py
openlane/config/flow.py
openlane/config/pdk_compat.py
openlane/config/preprocessor.py
openlane/config/removals.py
openlane/config/variable.py
openlane/container.py
openlane/env_info.py
openlane/examples/spm/config.yaml
openlane/examples/spm/pin_order.cfg
openlane/examples/spm/src/impl.sdc
openlane/examples/spm/src/signoff.sdc
openlane/examples/spm/src/spm.v
openlane/examples/spm/verify/spm_tb.v
openlane/examples/spm-user_project_wrapper/SPM_example.v
openlane/examples/spm-user_project_wrapper/base_sdc_file.sdc
openlane/examples/spm-user_project_wrapper/config-tut.json
openlane/examples/spm-user_project_wrapper/config.json
openlane/examples/spm-user_project_wrapper/defines.v
openlane/examples/spm-user_project_wrapper/template.def
openlane/examples/spm-user_project_wrapper/user_project_wrapper.v
openlane/flows/__init__.py
openlane/flows/builtins.py
openlane/flows/classic.py
openlane/flows/cli.py
openlane/flows/flow.py
openlane/flows/misc.py
openlane/flows/optimizing.py
openlane/flows/sequential.py
openlane/flows/synth_explore.py
openlane/logging/__init__.py
openlane/logging/logger.py
openlane/open_pdks_rev
openlane/plugins.py
openlane/py.typed
openlane/scripts/base.sdc
openlane/scripts/klayout/Readme.md
openlane/scripts/klayout/open_design.py
openlane/scripts/klayout/render.py
openlane/scripts/klayout/stream_out.py
openlane/scripts/klayout/xml_drc_report_to_json.py
openlane/scripts/klayout/xor.drc
openlane-2.3.9.dist-info/METADATA
openlane-2.3.9.dist-info/WHEEL
openlane-2.3.9.dist-info/entry_points.txt
openlane-2.3.9.dist-info/RECORD
