Metadata-Version: 2.1
Name: openlane
Version: 2.3.9
Summary: An infrastructure for implementing chip design flows
Home-page: https://efabless.com
License: Apache-2.0
Author: Efabless Corporation and Contributors
Author-email: donn@efabless.com
Requires-Python: >=3.8,<4
Classifier: License :: OSI Approved :: Apache Software License
Classifier: Programming Language :: Python :: 3
Classifier: Programming Language :: Python :: 3.8
Classifier: Programming Language :: Python :: 3.9
Classifier: Programming Language :: Python :: 3.10
Classifier: Programming Language :: Python :: 3.11
Classifier: Programming Language :: Python :: 3.12
Classifier: Programming Language :: Python :: 3.13
Requires-Dist: click (>=8,<9)
Requires-Dist: cloup (>=3.0.5,<4)
Requires-Dist: deprecated (>=1.2.10,<2)
Requires-Dist: httpx (>=0.22.0,<0.29)
Requires-Dist: ioplace-parser (>=0.3.0,<0.5.0)
Requires-Dist: klayout (>=0.29.0,<0.30.0)
Requires-Dist: libparse (>=0.3.1,<1)
Requires-Dist: lxml (>=4.9.0)
Requires-Dist: psutil (>=5.9.0)
Requires-Dist: pyyaml (>=5,<7)
Requires-Dist: rapidfuzz (>=3.9.0,<4)
Requires-Dist: rich (>=12,<14)
Requires-Dist: semver (>=3.0.2,<4.0.0)
Requires-Dist: volare (>=0.16.0)
Requires-Dist: yamlcore (>=0.0.2,<0.0.3)
Project-URL: Documentation, https://openlane.readthedocs.io
Project-URL: Repository, https://github.com/efabless/openlane
